<?xml version="1.0" encoding="UTF-8"?>
<Label>
	<Section name="adverse reactions">
		<sentence start="0" len="23"/>
		<sentence start="24" len="24"/>
		<sentence start="25" len="104"/>
		<sentence start="105" len="105"/>
		<sentence start="106" len="106"/>
		<sentence start="107" len="107"/>
		<sentence start="108" len="165"/>
		<sentence start="166" len="222"/>
		<sentence start="223" len="303"/>
		<sentence start="304" len="329"/>
		<sentence start="330" len="331"/>
		<sentence start="332" len="332"/>
		<sentence start="333" len="466"/>
		<sentence start="467" len="467"/>
		<sentence start="468" len="468"/>
		<sentence start="469" len="469"/>
		<sentence start="470" len="471"/>
		<sentence start="472" len="472"/>
		<sentence start="473" len="505"/>
		<sentence start="506" len="506"/>
		<sentence start="507" len="772"/>
		<sentence start="773" len="773"/>
		<sentence start="774" len="774"/>
		<sentence start="775" len="775"/>
		<sentence start="776" len="908"/>
		<sentence start="909" len="909"/>
		<sentence start="910" len="910"/>
		<sentence start="911" len="911"/>
		<sentence start="912" len="982"/>
		<sentence start="983" len="983"/>
		<sentence start="984" len="984"/>
		<sentence start="985" len="985"/>
		<sentence start="986" len="1057"/>
		<sentence start="1058" len="1058"/>
		<sentence start="1059" len="1059"/>
		<sentence start="1060" len="1060"/>
		<sentence start="1061" len="1167"/>
		<sentence start="1168" len="1168"/>
		<sentence start="1169" len="1169"/>
		<sentence start="1170" len="1170"/>
		<sentence start="1171" len="1235"/>
		<sentence start="1236" len="1311"/>
		<sentence start="1312" len="1312"/>
		<sentence start="1313" len="1313"/>
		<sentence start="1314" len="1314"/>
		<sentence start="1315" len="1921"/>
		<sentence start="1922" len="2030"/>
		<sentence start="2031" len="2139"/>
		<sentence start="2140" len="2217"/>
		<sentence start="2219" len="2593"/>
		<sentence start="2595" len="2810"/>
		<sentence start="2812" len="2881"/>
		<sentence start="2882" len="2998"/>
		<sentence start="2999" len="3000"/>
		<sentence start="3001" len="3001"/>
		<sentence start="3002" len="3050"/>
		<sentence start="3051" len="3128"/>
		<sentence start="3129" len="3129"/>
		<sentence start="3130" len="3130"/>
		<sentence start="3131" len="3131"/>
		<sentence start="3132" len="3263"/>
		<sentence start="3264" len="3264"/>
		<sentence start="3265" len="3265"/>
		<sentence start="3266" len="3266"/>
		<sentence start="3267" len="3326"/>
		<sentence start="3327" len="3327"/>
		<sentence start="3328" len="3328"/>
		<sentence start="3329" len="3329"/>
		<sentence start="3330" len="3457"/>
		<sentence start="3458" len="3811"/>
		<sentence start="3812" len="4031"/>
		<sentence start="4032" len="4227"/>
		<sentence start="4228" len="4228"/>
		<sentence start="4229" len="4229"/>
		<sentence start="4230" len="4230"/>
		<sentence start="4231" len="4259"/>
		<sentence start="4260" len="4260"/>
		<sentence start="4261" len="4261"/>
		<sentence start="4262" len="4262"/>
		<sentence start="4263" len="4628"/>
		<sentence start="4629" len="4736"/>
		<sentence start="4737" len="5113"/>
		<sentence start="5115" len="5334"/>
		<sentence start="5335" len="5485"/>
		<sentence start="5486" len="5487"/>
		<sentence start="5488" len="5488"/>
		<sentence start="5489" len="5526"/>
		<sentence start="5527" len="5527"/>
		<sentence start="5528" len="5528"/>
		<sentence start="5529" len="5529"/>
		<sentence start="5530" len="5617"/>
		<sentence start="5618" len="5618"/>
		<sentence start="5619" len="5619"/>
		<sentence start="5620" len="5620"/>
		<sentence start="5621" len="5775"/>
		<sentence start="5776" len="5839"/>
		<sentence start="5840" len="5842"/>
		<sentence start="5843" len="5898"/>
		<sentence start="5899" len="5954"/>
		<sentence start="5955" len="6010"/>
		<sentence start="6011" len="6118"/>
		<sentence start="6119" len="6120"/>
		<sentence start="6121" len="6121"/>
		<sentence start="6122" len="6200"/>
		<sentence start="6201" len="6201"/>
		<sentence start="6202" len="6202"/>
		<sentence start="6203" len="6203"/>
		<sentence start="6204" len="6920"/>
		<sentence start="6921" len="7114"/>
		<sentence start="7116" len="7181"/>
		<sentence start="7183" len="7256"/>
		<sentence start="7257" len="7569"/>
		<sentence start="7570" len="7571"/>
		<sentence start="7572" len="7572"/>
		<sentence start="7573" len="7612"/>
		<sentence start="7613" len="7613"/>
		<sentence start="7614" len="7614"/>
		<sentence start="7615" len="7615"/>
		<sentence start="7616" len="7704"/>
		<sentence start="7705" len="7705"/>
		<sentence start="7706" len="7706"/>
		<sentence start="7707" len="7707"/>
		<sentence start="7708" len="7833"/>
		<sentence start="7834" len="7896"/>
		<sentence start="7897" len="7899"/>
		<sentence start="7900" len="7947"/>
		<sentence start="7948" len="7995"/>
		<sentence start="7996" len="8043"/>
		<sentence start="8044" len="8068"/>
		<sentence start="8069" len="8070"/>
		<sentence start="8071" len="8071"/>
		<sentence start="8072" len="8286"/>
		<sentence start="8287" len="8510"/>
		<sentence start="8511" len="8656"/>
		<sentence start="8657" len="8769"/>
		<sentence start="8770" len="8770"/>
		<sentence start="8771" len="8771"/>
		<sentence start="8772" len="8772"/>
		<sentence start="8773" len="8799"/>
		<sentence start="8800" len="8800"/>
		<sentence start="8801" len="8801"/>
		<sentence start="8802" len="8802"/>
		<sentence start="8803" len="8820"/>
		<sentence start="8821" len="8821"/>
		<sentence start="8822" len="8822"/>
		<sentence start="8823" len="8823"/>
		<sentence start="8824" len="8967"/>
		<sentence start="8968" len="9037"/>
		<sentence start="9038" len="9124"/>
		<sentence start="9125" len="9125"/>
		<sentence start="9126" len="9126"/>
		<sentence start="9127" len="9127"/>
		<sentence start="9128" len="9277"/>
		<sentence start="9278" len="9376"/>
		<sentence start="9377" len="9451"/>
		<sentence start="9452" len="9452"/>
		<sentence start="9453" len="9453"/>
		<sentence start="9454" len="9454"/>
		<sentence start="9455" len="9473"/>
		<sentence start="9474" len="9474"/>
		<sentence start="9475" len="9475"/>
		<sentence start="9476" len="9476"/>
		<sentence start="9477" len="9640"/>
		<sentence start="9641" len="9748"/>
		<sentence start="9749" len="9864"/>
		<sentence start="9865" len="10030"/>
		<sentence start="10031" len="10031"/>
		<sentence start="10032" len="10032"/>
		<sentence start="10033" len="10033"/>
		<sentence start="10034" len="10179"/>
		<sentence start="10180" len="10317"/>
		<sentence start="10318" len="10318"/>
		<sentence start="10319" len="10319"/>
		<sentence start="10320" len="10320"/>
		<sentence start="10321" len="10375"/>
	</Section>

	<Section name="warnings and precautions">
		<sentence start="0" len="30"/>
		<sentence start="31" len="31"/>
		<sentence start="32" len="32"/>
		<sentence start="33" len="33"/>
		<sentence start="34" len="149"/>
		<sentence start="150" len="199"/>
		<sentence start="201" len="209"/>
		<sentence start="210" len="285"/>
		<sentence start="287" len="295"/>
		<sentence start="296" len="300"/>
		<sentence start="301" len="302"/>
		<sentence start="303" len="303"/>
		<sentence start="304" len="338"/>
		<sentence start="339" len="339"/>
		<sentence start="340" len="340"/>
		<sentence start="341" len="341"/>
		<sentence start="342" len="469"/>
		<sentence start="470" len="470"/>
		<sentence start="471" len="471"/>
		<sentence start="472" len="472"/>
		<sentence start="473" len="535"/>
		<sentence start="536" len="696"/>
		<sentence start="697" len="697"/>
		<sentence start="698" len="698"/>
		<sentence start="699" len="699"/>
		<sentence start="700" len="744"/>
		<sentence start="745" len="745"/>
		<sentence start="746" len="746"/>
		<sentence start="747" len="747"/>
		<sentence start="748" len="866"/>
		<sentence start="867" len="1068"/>
		<sentence start="1069" len="1069"/>
		<sentence start="1070" len="1070"/>
		<sentence start="1071" len="1071"/>
		<sentence start="1072" len="1090"/>
		<sentence start="1091" len="1091"/>
		<sentence start="1092" len="1092"/>
		<sentence start="1093" len="1093"/>
		<sentence start="1094" len="1179"/>
		<sentence start="1180" len="1452"/>
		<sentence start="1453" len="1453"/>
		<sentence start="1454" len="1454"/>
		<sentence start="1455" len="1455"/>
		<sentence start="1456" len="1578"/>
		<sentence start="1579" len="1721"/>
		<sentence start="1722" len="1722"/>
		<sentence start="1723" len="1723"/>
		<sentence start="1724" len="1724"/>
		<sentence start="1725" len="1917"/>
		<sentence start="1918" len="2042"/>
		<sentence start="2043" len="2043"/>
		<sentence start="2044" len="2044"/>
		<sentence start="2045" len="2045"/>
		<sentence start="2046" len="2084"/>
		<sentence start="2085" len="2085"/>
		<sentence start="2086" len="2086"/>
		<sentence start="2087" len="2087"/>
		<sentence start="2088" len="2186"/>
		<sentence start="2187" len="2317"/>
		<sentence start="2318" len="2430"/>
		<sentence start="2431" len="2483"/>
		<sentence start="2484" len="2484"/>
		<sentence start="2485" len="2485"/>
		<sentence start="2486" len="2486"/>
		<sentence start="2487" len="2523"/>
		<sentence start="2524" len="2524"/>
		<sentence start="2525" len="2525"/>
		<sentence start="2526" len="2526"/>
		<sentence start="2527" len="2595"/>
		<sentence start="2596" len="2678"/>
		<sentence start="2679" len="2795"/>
	</Section>

	<Section name="boxed warnings">
		<sentence start="0" len="0"/>
		<sentence start="1" len="1"/>
		<sentence start="2" len="93"/>
		<sentence start="94" len="94"/>
		<sentence start="95" len="169"/>
		<sentence start="170" len="170"/>
		<sentence start="171" len="177"/>
		<sentence start="179" len="194"/>
		<sentence start="195" len="195"/>
		<sentence start="196" len="196"/>
		<sentence start="197" len="197"/>
		<sentence start="198" len="304"/>
		<sentence start="305" len="427"/>
		<sentence start="428" len="540"/>
		<sentence start="541" len="605"/>
		<sentence start="606" len="686"/>
		<sentence start="687" len="695"/>
		<sentence start="697" len="738"/>
		<sentence start="739" len="740"/>
		<sentence start="741" len="741"/>
		<sentence start="742" len="865"/>
		<sentence start="866" len="959"/>
		<sentence start="960" len="961"/>
		<sentence start="962" len="962"/>
		<sentence start="963" len="1028"/>
		<sentence start="1029" len="1029"/>
		<sentence start="1030" len="1030"/>
		<sentence start="1031" len="1031"/>
		<sentence start="1032" len="1050"/>
		<sentence start="1051" len="1051"/>
		<sentence start="1052" len="1052"/>
		<sentence start="1053" len="1053"/>
		<sentence start="1054" len="1160"/>
		<sentence start="1161" len="1283"/>
		<sentence start="1284" len="1396"/>
		<sentence start="1397" len="1461"/>
		<sentence start="1462" len="1542"/>
		<sentence start="1543" len="1590"/>
		<sentence start="1591" len="1592"/>
		<sentence start="1593" len="1593"/>
		<sentence start="1594" len="1699"/>
		<sentence start="1700" len="1718"/>
	</Section>

</Label>