<?xml version="1.0" encoding="UTF-8"?>
<Label>
	<Section name="adverse reactions">
		<sentence start="0" len="23"/>
		<sentence start="24" len="24"/>
		<sentence start="25" len="104"/>
		<sentence start="105" len="105"/>
		<sentence start="106" len="106"/>
		<sentence start="107" len="107"/>
		<sentence start="108" len="164"/>
		<sentence start="165" len="223"/>
		<sentence start="224" len="319"/>
		<sentence start="320" len="489"/>
		<sentence start="490" len="499"/>
		<sentence start="500" len="501"/>
		<sentence start="502" len="502"/>
		<sentence start="503" len="505"/>
		<sentence start="506" len="506"/>
		<sentence start="507" len="507"/>
		<sentence start="508" len="508"/>
		<sentence start="509" len="673"/>
		<sentence start="674" len="674"/>
		<sentence start="675" len="675"/>
		<sentence start="676" len="676"/>
		<sentence start="677" len="678"/>
		<sentence start="679" len="679"/>
		<sentence start="680" len="713"/>
		<sentence start="714" len="714"/>
		<sentence start="715" len="980"/>
		<sentence start="981" len="981"/>
		<sentence start="982" len="982"/>
		<sentence start="983" len="983"/>
		<sentence start="984" len="1017"/>
		<sentence start="1018" len="1018"/>
		<sentence start="1019" len="1019"/>
		<sentence start="1020" len="1020"/>
		<sentence start="1021" len="1335"/>
		<sentence start="1336" len="1336"/>
		<sentence start="1337" len="1337"/>
		<sentence start="1338" len="1338"/>
		<sentence start="1339" len="1592"/>
		<sentence start="1593" len="1593"/>
		<sentence start="1594" len="1594"/>
		<sentence start="1595" len="1595"/>
		<sentence start="1596" len="1605"/>
		<sentence start="1606" len="1698"/>
		<sentence start="1699" len="1782"/>
		<sentence start="1783" len="1893"/>
		<sentence start="1894" len="1896"/>
		<sentence start="1897" len="2007"/>
		<sentence start="2008" len="2118"/>
		<sentence start="2119" len="2239"/>
		<sentence start="2240" len="2350"/>
		<sentence start="2351" len="2461"/>
		<sentence start="2462" len="2572"/>
		<sentence start="2573" len="2683"/>
		<sentence start="2684" len="2794"/>
		<sentence start="2795" len="2905"/>
		<sentence start="2906" len="3016"/>
		<sentence start="3017" len="3127"/>
		<sentence start="3128" len="3238"/>
		<sentence start="3239" len="3349"/>
		<sentence start="3350" len="3643"/>
		<sentence start="3644" len="3645"/>
		<sentence start="3646" len="3646"/>
		<sentence start="3647" len="3740"/>
		<sentence start="3741" len="3741"/>
		<sentence start="3742" len="3742"/>
		<sentence start="3743" len="3743"/>
		<sentence start="3744" len="3765"/>
		<sentence start="3766" len="3766"/>
		<sentence start="3767" len="3767"/>
		<sentence start="3768" len="3768"/>
		<sentence start="3769" len="4139"/>
		<sentence start="4140" len="4368"/>
		<sentence start="4369" len="4369"/>
		<sentence start="4370" len="4370"/>
		<sentence start="4371" len="4371"/>
		<sentence start="4372" len="4625"/>
		<sentence start="4626" len="4717"/>
		<sentence start="4718" len="4718"/>
		<sentence start="4719" len="4719"/>
		<sentence start="4720" len="4720"/>
		<sentence start="4721" len="4744"/>
		<sentence start="4745" len="4745"/>
		<sentence start="4746" len="4746"/>
		<sentence start="4747" len="4747"/>
		<sentence start="4748" len="5046"/>
		<sentence start="5047" len="5217"/>
		<sentence start="5218" len="5371"/>
		<sentence start="5372" len="5671"/>
		<sentence start="5673" len="5676"/>
		<sentence start="5677" len="5677"/>
		<sentence start="5678" len="5678"/>
		<sentence start="5679" len="5679"/>
		<sentence start="5680" len="5723"/>
		<sentence start="5724" len="5724"/>
		<sentence start="5725" len="5725"/>
		<sentence start="5726" len="5726"/>
		<sentence start="5727" len="5901"/>
		<sentence start="5902" len="6041"/>
		<sentence start="6042" len="6349"/>
		<sentence start="6350" len="6350"/>
		<sentence start="6351" len="6351"/>
		<sentence start="6352" len="6352"/>
		<sentence start="6353" len="6374"/>
		<sentence start="6375" len="6375"/>
		<sentence start="6376" len="6556"/>
		<sentence start="6557" len="6691"/>
		<sentence start="6692" len="6817"/>
		<sentence start="6818" len="6941"/>
		<sentence start="6942" len="6942"/>
		<sentence start="6943" len="6943"/>
		<sentence start="6944" len="6944"/>
		<sentence start="6945" len="7132"/>
		<sentence start="7133" len="7346"/>
		<sentence start="7347" len="7492"/>
		<sentence start="7493" len="7493"/>
		<sentence start="7494" len="7494"/>
		<sentence start="7495" len="7495"/>
		<sentence start="7496" len="7528"/>
		<sentence start="7529" len="7529"/>
		<sentence start="7530" len="7614"/>
		<sentence start="7615" len="7825"/>
		<sentence start="7826" len="7826"/>
		<sentence start="7827" len="7827"/>
		<sentence start="7828" len="7828"/>
		<sentence start="7829" len="8002"/>
		<sentence start="8003" len="8073"/>
	</Section>

	<Section name="warnings and precautions">
		<sentence start="0" len="30"/>
		<sentence start="31" len="31"/>
		<sentence start="32" len="32"/>
		<sentence start="33" len="33"/>
		<sentence start="34" len="97"/>
		<sentence start="98" len="174"/>
		<sentence start="175" len="256"/>
		<sentence start="257" len="267"/>
		<sentence start="268" len="481"/>
		<sentence start="482" len="579"/>
		<sentence start="580" len="590"/>
		<sentence start="591" len="689"/>
		<sentence start="690" len="758"/>
		<sentence start="759" len="769"/>
		<sentence start="770" len="834"/>
		<sentence start="835" len="938"/>
		<sentence start="939" len="949"/>
		<sentence start="950" len="1035"/>
		<sentence start="1036" len="1046"/>
		<sentence start="1047" len="1131"/>
		<sentence start="1132" len="1192"/>
		<sentence start="1193" len="1203"/>
		<sentence start="1204" len="1208"/>
		<sentence start="1209" len="1210"/>
		<sentence start="1211" len="1211"/>
		<sentence start="1212" len="1229"/>
		<sentence start="1230" len="1230"/>
		<sentence start="1231" len="1231"/>
		<sentence start="1232" len="1232"/>
		<sentence start="1233" len="1323"/>
		<sentence start="1324" len="1458"/>
		<sentence start="1459" len="1459"/>
		<sentence start="1460" len="1460"/>
		<sentence start="1461" len="1461"/>
		<sentence start="1462" len="1556"/>
		<sentence start="1557" len="1652"/>
		<sentence start="1653" len="1748"/>
		<sentence start="1749" len="1881"/>
		<sentence start="1882" len="1882"/>
		<sentence start="1883" len="1883"/>
		<sentence start="1884" len="1884"/>
		<sentence start="1885" len="2003"/>
		<sentence start="2004" len="2212"/>
		<sentence start="2213" len="2293"/>
		<sentence start="2294" len="2294"/>
		<sentence start="2295" len="2295"/>
		<sentence start="2296" len="2296"/>
		<sentence start="2297" len="2364"/>
		<sentence start="2365" len="2365"/>
		<sentence start="2366" len="2366"/>
		<sentence start="2367" len="2367"/>
		<sentence start="2368" len="2637"/>
		<sentence start="2638" len="2712"/>
		<sentence start="2713" len="2713"/>
		<sentence start="2714" len="2714"/>
		<sentence start="2715" len="2715"/>
		<sentence start="2716" len="2876"/>
		<sentence start="2877" len="3005"/>
		<sentence start="3006" len="3006"/>
		<sentence start="3007" len="3007"/>
		<sentence start="3008" len="3008"/>
		<sentence start="3009" len="3058"/>
		<sentence start="3059" len="3059"/>
		<sentence start="3060" len="3060"/>
		<sentence start="3061" len="3061"/>
		<sentence start="3062" len="3159"/>
		<sentence start="3160" len="3160"/>
		<sentence start="3161" len="3161"/>
		<sentence start="3162" len="3162"/>
		<sentence start="3163" len="3233"/>
		<sentence start="3234" len="3314"/>
		<sentence start="3315" len="3512"/>
		<sentence start="3513" len="3647"/>
		<sentence start="3648" len="3648"/>
		<sentence start="3649" len="3649"/>
		<sentence start="3650" len="3650"/>
		<sentence start="3651" len="3671"/>
		<sentence start="3672" len="3672"/>
		<sentence start="3673" len="3673"/>
		<sentence start="3674" len="3674"/>
		<sentence start="3675" len="3755"/>
		<sentence start="3756" len="3880"/>
		<sentence start="3881" len="4000"/>
		<sentence start="4001" len="4001"/>
		<sentence start="4002" len="4002"/>
		<sentence start="4003" len="4003"/>
		<sentence start="4004" len="4132"/>
		<sentence start="4133" len="4133"/>
		<sentence start="4134" len="4134"/>
		<sentence start="4135" len="4135"/>
		<sentence start="4136" len="4357"/>
		<sentence start="4358" len="4462"/>
		<sentence start="4463" len="4675"/>
		<sentence start="4676" len="4676"/>
		<sentence start="4677" len="4677"/>
		<sentence start="4678" len="4678"/>
		<sentence start="4679" len="4713"/>
		<sentence start="4714" len="4714"/>
		<sentence start="4715" len="4715"/>
		<sentence start="4716" len="4716"/>
		<sentence start="4717" len="4820"/>
		<sentence start="4821" len="5004"/>
		<sentence start="5005" len="5005"/>
		<sentence start="5006" len="5006"/>
		<sentence start="5007" len="5007"/>
		<sentence start="5008" len="5065"/>
		<sentence start="5066" len="5066"/>
		<sentence start="5067" len="5067"/>
		<sentence start="5068" len="5068"/>
		<sentence start="5069" len="5231"/>
		<sentence start="5232" len="5366"/>
		<sentence start="5367" len="5486"/>
		<sentence start="5487" len="5487"/>
		<sentence start="5488" len="5488"/>
		<sentence start="5489" len="5489"/>
		<sentence start="5490" len="5589"/>
		<sentence start="5590" len="5666"/>
		<sentence start="5667" len="5812"/>
		<sentence start="5813" len="5847"/>
		<sentence start="5848" len="5848"/>
		<sentence start="5849" len="5849"/>
		<sentence start="5850" len="5850"/>
		<sentence start="5851" len="5941"/>
		<sentence start="5942" len="5942"/>
		<sentence start="5943" len="5943"/>
		<sentence start="5944" len="5944"/>
		<sentence start="5945" len="5966"/>
		<sentence start="5967" len="5967"/>
		<sentence start="5968" len="5968"/>
		<sentence start="5969" len="5969"/>
		<sentence start="5970" len="6133"/>
		<sentence start="6134" len="6209"/>
		<sentence start="6210" len="6376"/>
		<sentence start="6377" len="6585"/>
		<sentence start="6586" len="6586"/>
		<sentence start="6587" len="6587"/>
		<sentence start="6588" len="6588"/>
		<sentence start="6589" len="6718"/>
		<sentence start="6719" len="6719"/>
		<sentence start="6720" len="6720"/>
		<sentence start="6721" len="6721"/>
		<sentence start="6722" len="6751"/>
		<sentence start="6752" len="6752"/>
		<sentence start="6753" len="6753"/>
		<sentence start="6754" len="6754"/>
		<sentence start="6755" len="6897"/>
		<sentence start="6898" len="7052"/>
		<sentence start="7054" len="7253"/>
	</Section>

</Label>